watermelon/__init__.py
watermelon/__main__.py
watermelon/event/__init__.py
watermelon/event/event.py
watermelon/event/utils.py
watermelon/resources/db.json
watermelon_todo_list-0.0.3.dist-info/LICENSE
watermelon_todo_list-0.0.3.dist-info/METADATA
watermelon_todo_list-0.0.3.dist-info/WHEEL
watermelon_todo_list-0.0.3.dist-info/entry_points.txt
watermelon_todo_list-0.0.3.dist-info/top_level.txt
watermelon_todo_list-0.0.3.dist-info/RECORD
