Metadata-Version: 2.1
Name: watermelon-todo-list
Version: 0.0.3
Summary: watermelon, inspired by tomato impl by python
Home-page: https://github.com/Watermelon-Family/watermelon
Author: ruanjiancheng
Author-email: 1434919953@qq.com
Classifier: Programming Language :: Python :: 3
Classifier: Operating System :: OS Independent
Requires-Python: >=3.7
License-File: LICENSE
Requires-Dist: python-dateutil (<5.0.0,>=2.7.0)
Requires-Dist: prettytable (<5.0.0,>=3.2.0)
